LICENSE.txt
MANIFEST.in
setup.cfg
setup.py
passer/__init__.py
passer/frontend_client.py
passer.egg-info/PKG-INFO
passer.egg-info/SOURCES.txt
passer.egg-info/dependency_links.txt
passer.egg-info/top_level.txt
passer/__pycache__/__init__.cpython-35.pyc
passer/daemon/__init__.py
passer/daemon/config.py
passer/daemon/monitor/__init__.py
passer/daemon/monitor/fifo_task_scheduler.py
passer/daemon/monitor/no_queue_task_scheduler.py
passer/daemon/monitor/node_monitor.py
passer/daemon/monitor/node_monitor_state.py
passer/daemon/monitor/priority_task_scheduler.py
passer/daemon/monitor/round_robin_task_scheduler.py
passer/daemon/monitor/task_launcher_service.py
passer/daemon/monitor/task_scheduler.py
passer/daemon/scheduler/__init__.py
passer/daemon/scheduler/cancellation_service.py
passer/daemon/scheduler/constrained_task_placer.py
passer/daemon/scheduler/scheduler.py
passer/daemon/scheduler/task_placer.py
passer/daemon/scheduler/unconsrained_task_placer.py
passer/proto/__init__.py
passer/proto/types_pb2.py