Metadata-Version: 1.0
Name: passer
Version: 0.0.1
Summary: A Python 3.5 implementation of the Sparrow scheduler
Home-page: https://github.com/hypoalex/passer
Author: Alex Caudill
Author-email: nobody@nowhere.io
License: UNKNOWN
Platform: UNKNOWN
